jaccard_concentration_index/__init__.py
jaccard_concentration_index/jaccard_concentration_index.py
jaccard_concentration_index-1.0.5.dist-info/licenses/LICENSE
jaccard_concentration_index-1.0.5.dist-info/METADATA
jaccard_concentration_index-1.0.5.dist-info/WHEEL
jaccard_concentration_index-1.0.5.dist-info/top_level.txt
jaccard_concentration_index-1.0.5.dist-info/RECORD
