Metadata-Version: 2.4
Name: jaccard-concentration-index
Version: 1.0.5
Summary: A library for clustering evaluation based on the distribution of predicted cluster mass across true clusters.
Home-page: https://github.com/RandyWAidoo/Jaccard-Concentration-Index
Author: Randolph Wiredu-Aidoo
Author-email: randyaidoo.dev@gmail.com
License: MIT
Classifier: Programming Language :: Python :: 3
Classifier: License :: OSI Approved :: MIT License
Classifier: Operating System :: OS Independent
Requires-Python: >=3.6
License-File: LICENSE
Requires-Dist: numpy>=1.21.0
Requires-Dist: scikit-learn>=0.24.0
Dynamic: author
Dynamic: author-email
Dynamic: classifier
Dynamic: description
Dynamic: description-content-type
Dynamic: home-page
Dynamic: license
Dynamic: license-file
Dynamic: requires-dist
Dynamic: requires-python
Dynamic: summary
